odoo/addons/account_receipt_base/README.rst
odoo/addons/account_receipt_base/__init__.py
odoo/addons/account_receipt_base/__manifest__.py
odoo/addons/account_receipt_base/i18n/account_receipt_base.pot
odoo/addons/account_receipt_base/i18n/es.po
odoo/addons/account_receipt_base/i18n/it.po
odoo/addons/account_receipt_base/models/__init__.py
odoo/addons/account_receipt_base/models/account_fiscal_position.py
odoo/addons/account_receipt_base/models/account_move.py
odoo/addons/account_receipt_base/models/res_partner.py
odoo/addons/account_receipt_base/readme/CONFIGURE.rst
odoo/addons/account_receipt_base/readme/CONTRIBUTORS.rst
odoo/addons/account_receipt_base/readme/DESCRIPTION.rst
odoo/addons/account_receipt_base/reports/__init__.py
odoo/addons/account_receipt_base/reports/account_invoice_report.py
odoo/addons/account_receipt_base/reports/account_invoice_report_views.xml
odoo/addons/account_receipt_base/static/description/icon.png
odoo/addons/account_receipt_base/static/description/index.html
odoo/addons/account_receipt_base/tests/__init__.py
odoo/addons/account_receipt_base/tests/test_fiscal_position.py
odoo/addons/account_receipt_base/tests/test_partner.py
odoo/addons/account_receipt_base/tests/test_receipt.py
odoo/addons/account_receipt_base/views/account_fiscal_position_views.xml
odoo/addons/account_receipt_base/views/account_move_views.xml
odoo/addons/account_receipt_base/views/res_partner_views.xml
odoo14_addon_account_receipt_base-14.0.1.0.1.dev8.dist-info/METADATA
odoo14_addon_account_receipt_base-14.0.1.0.1.dev8.dist-info/WHEEL
odoo14_addon_account_receipt_base-14.0.1.0.1.dev8.dist-info/top_level.txt
odoo14_addon_account_receipt_base-14.0.1.0.1.dev8.dist-info/RECORD
